pythontfvars/__init__.py
pythontfvars/main.py
tfvars/__init__.py
tfvars/main.py
python_tfvars-0.1.0.dist-info/METADATA
python_tfvars-0.1.0.dist-info/WHEEL
python_tfvars-0.1.0.dist-info/top_level.txt
python_tfvars-0.1.0.dist-info/RECORD
