Metadata-Version: 2.1
Name: python-tfvars
Version: 0.1.0
Summary: read secrets from terraform tfvars files
Home-page: https://gitlab.com/shindagger/python-tfvars
Author: Andy Klier
Author-email: andyklier@gmail.com
License: UNKNOWN
Platform: UNKNOWN
Classifier: Programming Language :: Python :: 3
Classifier: License :: OSI Approved :: MIT License
Classifier: Operating System :: OS Independent
Requires-Python: >=3.6
Requires-Dist: setuptools
